datarobot_predict/__init__.py
datarobot_predict/_base_scoring_code.py
datarobot_predict/deployment.py
datarobot_predict/lib/batch-processor.jar
datarobot_predict/lib/scoring-code-spark-api.jar
datarobot_predict/scoring_code.py
datarobot_predict/spark_scoring_code.py
datarobot_predict-1.13.3.dist-info/LICENSE.txt
datarobot_predict-1.13.3.dist-info/METADATA
datarobot_predict-1.13.3.dist-info/WHEEL
datarobot_predict-1.13.3.dist-info/RECORD
