Metadata-Version: 2.1
Name: datarobot-predict
Version: 1.13.3
Summary: DataRobot Prediction Library
License: Apache-2.0
Author: DataRobot
Author-email: support@datarobot.com
Requires-Python: >=3.8
Classifier: License :: OSI Approved :: Apache Software License
Classifier: Programming Language :: Python :: 3
Classifier: Programming Language :: Python :: 3.8
Classifier: Programming Language :: Python :: 3.9
Classifier: Programming Language :: Python :: 3.10
Classifier: Programming Language :: Python :: 3.11
Classifier: Programming Language :: Python :: 3.12
Classifier: Programming Language :: Python :: 3.13
Requires-Dist: click (>=7,<9)
Requires-Dist: datarobot (>=2.17)
Requires-Dist: pandas (>=0.15)
Requires-Dist: py4j (>=0.10.7,<0.11.0)
Requires-Dist: requests (>=2.28.1)
Requires-Dist: requests-toolbelt (>=0.6)
Requires-Dist: urllib3 (>=1.23)
